compel/__init__.py
compel/compel.py
compel/conditioning_scheduler.py
compel/convenience_wrappers.py
compel/cross_attention_control.py
compel/diffusers_textual_inversion_manager.py
compel/embeddings_provider.py
compel/prompt_parser.py
compel-2.3.0.dist-info/licenses/LICENSE
compel-2.3.0.dist-info/METADATA
compel-2.3.0.dist-info/WHEEL
compel-2.3.0.dist-info/top_level.txt
compel-2.3.0.dist-info/RECORD
