Metadata-Version: 2.4
Name: compel
Version: 2.3.0
Summary: A prompting enhancement library for transformers-type text embedding systems.
Author-email: Damian Stewart <null@damianstewart.com>
Project-URL: Homepage, https://github.com/damian0815/compel
Project-URL: Bug Tracker, https://github.com/damian0815/compel/issues
Classifier: Programming Language :: Python :: 3
Classifier: License :: OSI Approved :: MIT License
Classifier: Operating System :: OS Independent
Requires-Python: >=3.7
License-File: LICENSE
Requires-Dist: diffusers>=0.11
Requires-Dist: notebook>=6.5.7
Requires-Dist: pyparsing~=3.0
Requires-Dist: torch
Requires-Dist: transformers~=4.25
Dynamic: license-file
